LICENSE
MANIFEST.in
Makefile
README
setup.cfg
setup.py
test/CASES
test/__init__.py
test/__init__.pyc
test/test_compile.py
test/test_import_one.py
test/test_parse_recipe.py
test/test_strip_extension.py
test/test_tiddlywiki.py
test/test_url_to_tiddler.py
test/test_wiki_to_tiddlers.py
test/__pycache__/test_compile.cpython-27-PYTEST.pyc
test/__pycache__/test_import_one.cpython-27-PYTEST.pyc
test/__pycache__/test_parse_recipe.cpython-27-PYTEST.pyc
test/__pycache__/test_strip_extension.cpython-27-PYTEST.pyc
test/__pycache__/test_tiddlywiki.cpython-27-PYTEST.pyc
test/__pycache__/test_url_to_tiddler.cpython-27-PYTEST.pyc
test/__pycache__/test_wiki_to_tiddlers.cpython-27-PYTEST.pyc
test/samples/peermore.png
test/samples/tiddlers.html
test/samples/tiddlers.wiki
test/samples/tiddlyweb.css
test/samples/alpha/Empty.tiddler
test/samples/alpha/Greetings.tiddler
test/samples/alpha/Welcome.tid
test/samples/alpha/fnord.css
test/samples/alpha/fnord.css.meta
test/samples/alpha/index.html.recipe
test/samples/alpha/plugins/aplugin.js
test/samples/alpha/plugins/aplugin.js.meta
test/samples/alpha/plugins/bplugin.js
test/samples/alpha/plugins/bplugin.js.meta
test/samples/alpha/plugins/metaplugin.js
test/samples/alpha/plugins/metaplugin.js.meta
test/samples/beta/Hello.tid
test/samples/beta/buried/hole.js
test/samples/beta/buried/short.recipe
tiddlywebplugins/__init__.py
tiddlywebplugins/twimport.py
tiddlywebplugins.twimport.egg-info/PKG-INFO
tiddlywebplugins.twimport.egg-info/SOURCES.txt
tiddlywebplugins.twimport.egg-info/dependency_links.txt
tiddlywebplugins.twimport.egg-info/namespace_packages.txt
tiddlywebplugins.twimport.egg-info/not-zip-safe
tiddlywebplugins.twimport.egg-info/requires.txt
tiddlywebplugins.twimport.egg-info/top_level.txt